{"14976":{"built_by":"Morgan Giles (Teignmouth, England, U.K.)","ordered":"29 Jun 1940","laid_down":"","launched":"","commissioned":"8 May 1941","end_service":"","ordered_iso":"1940-06-29","laid_down_iso":null,"launched_iso":null,"commissioned_iso":"1941-05-08","end_service_iso":null,"history":"For disposal in January 1946","commanders":[],"url":"https://uboat.net/allies/warships/ship/14976.html","quality_flags":null},"14977":{"built_by":"Morgan Giles (Teignmouth, England, U.K.)","ordered":"29 Jun 1940","laid_down":"","launched":"","commissioned":"12 Jul 1941","end_service":"","ordered_iso":"1940-06-29","laid_down_iso":null,"launched_iso":null,"commissioned_iso":"1941-07-12","end_service_iso":null,"history":"Sold on 20 April 1959","commanders":[],"url":"https://uboat.net/allies/warships/ship/14977.html","quality_flags":null},"14978":{"built_by":"Berthon Boat (Lymington, England, U.K.)","ordered":"29 Jun 1940","laid_down":"","launched":"","commissioned":"6 Nov 1941","end_service":"","ordered_iso":"1940-06-29","laid_down_iso":null,"launched_iso":null,"commissioned_iso":"1941-11-06","end_service_iso":null,"history":"Stranded on 11 October 1943 near Tees and declared a total loss","commanders":[],"url":"https://uboat.net/allies/warships/ship/14978.html","quality_flags":null},"14979":{"built_by":"Berthon Boat (Lymington, England, U.K.)","ordered":"29 Jun 1940","laid_down":"","launched":"","commissioned":"14 Mar 1942","end_service":"","ordered_iso":"1940-06-29","laid_down_iso":null,"launched_iso":null,"commissioned_iso":"1942-03-14","end_service_iso":null,"history":"For disposal in July 1946","commanders":[],"url":"https://uboat.net/allies/warships/ship/14979.html","quality_flags":null},"14980":{"built_by":"David Hillyard Boatbuilders (Littlehampton,","ordered":"29 Jun 1940","laid_down":"","launched":"","commissioned":"18 Aug 1941","end_service":"","ordered_iso":"1940-06-29","laid_down_iso":null,"launched_iso":null,"commissioned_iso":"1941-08-18","end_service_iso":null,"history":"For disposal in August 1946","commanders":[],"url":"https://uboat.net/allies/warships/ship/14980.html","quality_flags":null},"14981":{"built_by":"David Hillyard Boatbuilders (Littlehampton,","ordered":"29 Jun 1940","laid_down":"","launched":"","commissioned":"30 Sep 1941","end_service":"","ordered_iso":"1940-06-29","laid_down_iso":null,"launched_iso":null,"commissioned_iso":"1941-09-30","end_service_iso":null,"history":"Sunk in an accident at ?Kilindili, Kenya on 13 October 1944","commanders":[],"url":"https://uboat.net/allies/warships/ship/14981.html","quality_flags":null},"14982":{"built_by":"Woods (Potter Heigham, England, U.K.)","ordered":"29 Jun 1940","laid_down":"","launched":"","commissioned":"8 Sep 1941","end_service":"","ordered_iso":"1940-06-29","laid_down_iso":null,"launched_iso":null,"commissioned_iso":"1941-09-08","end_service_iso":null,"history":"Transferred to China in 1947","commanders":[],"url":"https://uboat.net/allies/warships/ship/14982.html","quality_flags":null},"14983":{"built_by":"Woods (Potter Heigham, England, U.K.)","ordered":"29 Jun 1940","laid_down":"","launched":"","commissioned":"27 Sep 1941","end_service":"","ordered_iso":"1940-06-29","laid_down_iso":null,"launched_iso":null,"commissioned_iso":"1941-09-27","end_service_iso":null,"history":"Transferred to China in 1947","commanders":[],"url":"https://uboat.net/allies/warships/ship/14983.html","quality_flags":null},"14984":{"built_by":"Woods (Potter Heigham, England, U.K.)","ordered":"29 Jun 1940","laid_down":"","launched":"","commissioned":"12 Jan 1942","end_service":"23 Sep 1944","ordered_iso":"1940-06-29","laid_down_iso":null,"launched_iso":null,"commissioned_iso":"1942-01-12","end_service_iso":"1944-09-23","history":"Heavily damaged by an ammunition explosion at or off Poole on 6 August 1944, declared a total loss and paid off on 23 September 1944.","commanders":[],"url":"https://uboat.net/allies/warships/ship/14984.html","quality_flags":null},"14985":{"built_by":"Woods (Potter Heigham, England, U.K.)","ordered":"29 Jun 1940","laid_down":"","launched":"","commissioned":"23 Apr 1942","end_service":"May 1943","ordered_iso":"1940-06-29","laid_down_iso":null,"launched_iso":null,"commissioned_iso":"1942-04-23","end_service_iso":"1943-05-01","history":"Transferred to the Royal Indian Navy in May 1943","commanders":[],"url":"https://uboat.net/allies/warships/ship/14985.html","quality_flags":null},"14986":{"built_by":"Woods (Potter Heigham, England, U.K.)","ordered":"29 Jun 1940","laid_down":"","launched":"","commissioned":"May 1943","end_service":"","ordered_iso":"1940-06-29","laid_down_iso":null,"launched_iso":null,"commissioned_iso":"1943-05-01","end_service_iso":null,"history":"For disposal in June 1946","commanders":[],"url":"https://uboat.net/allies/warships/ship/14986.html","quality_flags":null},"14987":{"built_by":"Thornycroft (Singapore)","ordered":"26 Jul 1940","laid_down":"","launched":"","commissioned":"Jan 1942","end_service":"","ordered_iso":"1940-07-26","laid_down_iso":null,"launched_iso":null,"commissioned_iso":"1942-01-01","end_service_iso":null,"history":"Sunk by gunfire from Japanese surface vessels off Banka Strait on 16 February 1942","commanders":[],"url":"https://uboat.net/allies/warships/ship/14987.html","quality_flags":null},"14988":{"built_by":"Thornycroft (Singapore)","ordered":"26 Jul 1940","laid_down":"","launched":"","commissioned":"Jan 1942","end_service":"","ordered_iso":"1940-07-26","laid_down_iso":null,"launched_iso":null,"commissioned_iso":"1942-01-01","end_service_iso":null,"history":"Lost at Tandjong Priok, Netherlands East Indies on 1 March 1942","commanders":[],"url":"https://uboat.net/allies/warships/ship/14988.html","quality_flags":null},"14989":{"built_by":"Bolson (Poole, England, U.K.)","ordered":"26 Jul 1940","laid_down":"","launched":"","commissioned":"3 Jul 1941","end_service":"","ordered_iso":"1940-07-26","laid_down_iso":null,"launched_iso":null,"commissioned_iso":"1941-07-03","end_service_iso":null,"history":"Sold in 1947","commanders":[],"url":"https://uboat.net/allies/warships/ship/14989.html","quality_flags":null},"14990":{"built_by":"Blackmore (Bideford, U.K.)","ordered":"26 Jul 1940","laid_down":"","launched":"","commissioned":"16 Jul 1941","end_service":"","ordered_iso":"1940-07-26","laid_down_iso":null,"launched_iso":null,"commissioned_iso":"1941-07-16","end_service_iso":null,"history":"For disposal in November 1945","commanders":[],"url":"https://uboat.net/allies/warships/ship/14990.html","quality_flags":null},"14991":{"built_by":"Blackmore (Bideford, U.K.)","ordered":"26 Jul 1940","laid_down":"","launched":"","commissioned":"20 Aug 1941","end_service":"","ordered_iso":"1940-07-26","laid_down_iso":null,"launched_iso":null,"commissioned_iso":"1941-08-20","end_service_iso":null,"history":"For disposal in November 1945","commanders":[],"url":"https://uboat.net/allies/warships/ship/14991.html","quality_flags":null},"14992":{"built_by":"Moody (Southampton, England, U.K.)","ordered":"31 Jul 1940","laid_down":"","launched":"","commissioned":"8 May 1941","end_service":"","ordered_iso":"1940-07-31","laid_down_iso":null,"launched_iso":null,"commissioned_iso":"1941-05-08","end_service_iso":null,"history":"Sold to France in January 1948","commanders":[],"url":"https://uboat.net/allies/warships/ship/14992.html","quality_flags":null},"14993":{"built_by":"Moody (Southampton, England, U.K.)","ordered":"31 Jul 1940","laid_down":"","launched":"","commissioned":"25 Jun 1941","end_service":"","ordered_iso":"1940-07-31","laid_down_iso":null,"launched_iso":null,"commissioned_iso":"1941-06-25","end_service_iso":null,"history":"Transferred to China in 1947","commanders":[],"url":"https://uboat.net/allies/warships/ship/14993.html","quality_flags":null},"14994":{"built_by":"Watercraft Ltd. (East Moseley, England, U.K.)","ordered":"31 Jul 1940","laid_down":"","launched":"","commissioned":"28 May 1941","end_service":"","ordered_iso":"1940-07-31","laid_down_iso":null,"launched_iso":null,"commissioned_iso":"1941-05-28","end_service_iso":null,"history":"Captured by Germans/Italians at Tobruk on 20 June 1942","commanders":[],"url":"https://uboat.net/allies/warships/ship/14994.html","quality_flags":null},"14995":{"built_by":"Watercraft Ltd. (East Moseley, England, U.K.)","ordered":"31 Jul 1940","laid_down":"","launched":"","commissioned":"28 May 1941","end_service":"","ordered_iso":"1940-07-31","laid_down_iso":null,"launched_iso":null,"commissioned_iso":"1941-05-28","end_service_iso":null,"history":"Sold in 1948","commanders":[],"url":"https://uboat.net/allies/warships/ship/14995.html","quality_flags":null},"14996":{"built_by":"Sittingbourne Shipbuilding Co. (Shoreham, England, U.K.)","ordered":"14 Sep 1940","laid_down":"","launched":"","commissioned":"21 Aug 1941","end_service":"","ordered_iso":"1940-09-14","laid_down_iso":null,"launched_iso":null,"commissioned_iso":"1941-08-21","end_service_iso":null,"history":"Sold in November 1947","commanders":[],"url":"https://uboat.net/allies/warships/ship/14996.html","quality_flags":null},"14997":{"built_by":"Sittingbourne Shipbuilding Co. (Shoreham, England, U.K.)","ordered":"14 Sep 1940","laid_down":"","launched":"","commissioned":"13 Oct 1941","end_service":"30 Aug 1943","ordered_iso":"1940-09-14","laid_down_iso":null,"launched_iso":null,"commissioned_iso":"1941-10-13","end_service_iso":"1943-08-30","history":"Transferred to the Free French Navy on 30 August 1943","commanders":[],"url":"https://uboat.net/allies/warships/ship/14997.html","quality_flags":null},"14998":{"built_by":"Sittingbourne Shipbuilding Co. (Shoreham, England, U.K.)","ordered":"14 Sep 1940","laid_down":"","launched":"","commissioned":"30 Aug 1943","end_service":"","ordered_iso":"1940-09-14","laid_down_iso":null,"launched_iso":null,"commissioned_iso":"1943-08-30","end_service_iso":null,"history":"","commanders":[],"url":"https://uboat.net/allies/warships/ship/14998.html","quality_flags":null},"14999":{"built_by":"Robinson (Tewkesbury, England, U.K.)","ordered":"13 Aug 1940","laid_down":"","launched":"","commissioned":"18 May 1941","end_service":"1943","ordered_iso":"1940-08-13","laid_down_iso":null,"launched_iso":null,"commissioned_iso":"1941-05-18","end_service_iso":"1943-01-01","history":"Transferred to the Royal Indian Navy in 1943","commanders":[],"url":"https://uboat.net/allies/warships/ship/14999.html","quality_flags":null},"15000":{"built_by":"Robinson (Tewkesbury, England, U.K.)","ordered":"13 Aug 1940","laid_down":"","launched":"","commissioned":"1943","end_service":"","ordered_iso":"1940-08-13","laid_down_iso":null,"launched_iso":null,"commissioned_iso":"1943-01-01","end_service_iso":null,"history":"For disposal in 1946","commanders":[],"url":"https://uboat.net/allies/warships/ship/15000.html","quality_flags":null},"15001":{"built_by":"Robinson (Tewkesbury, England, U.K.)","ordered":"13 Aug 1940","laid_down":"","launched":"","commissioned":"1942","end_service":"7 Oct 1942","ordered_iso":"1940-08-13","laid_down_iso":null,"launched_iso":null,"commissioned_iso":"1942-01-01","end_service_iso":"1942-10-07","history":"Transferred to the Royal Australian Navy on 7 October 1942","commanders":[],"url":"https://uboat.net/allies/warships/ship/15001.html","quality_flags":null},"15002":{"built_by":"Robinson (Tewkesbury, England, U.K.)","ordered":"13 Aug 1940","laid_down":"","launched":"","commissioned":"7 Oct 1942","end_service":"","ordered_iso":"1940-08-13","laid_down_iso":null,"launched_iso":null,"commissioned_iso":"1942-10-07","end_service_iso":null,"history":"Sold on 24 January 1948","commanders":[],"url":"https://uboat.net/allies/warships/ship/15002.html","quality_flags":null},"15003":{"built_by":"Robinson (Lowestoft, England, U.K.)","ordered":"13 Aug 1940","laid_down":"","launched":"","commissioned":"11 Dec 1941","end_service":"","ordered_iso":"1940-08-13","laid_down_iso":null,"launched_iso":null,"commissioned_iso":"1941-12-11","end_service_iso":null,"history":"For disposal in August 1946","commanders":[],"url":"https://uboat.net/allies/warships/ship/15003.html","quality_flags":null},"15004":{"built_by":"McLean (Renfrew, Scotland, U.K.)","ordered":"2 Sep 1940","laid_down":"","launched":"","commissioned":"1 Aug 1941","end_service":"","ordered_iso":"1940-09-02","laid_down_iso":null,"launched_iso":null,"commissioned_iso":"1941-08-01","end_service_iso":null,"history":"Sold on 22 December 1945","commanders":["T/S.Lt. Ian Douglas Bertie Newsom, RNVR (24 May 1943 - 20 Apr 1944)","T/S.Lt. Merville Matthews, RNVR (20 Apr 1944 - 22 Oct 1944)","R T Hignell, RNVR (2 Jan 1945 - late 1945)"],"url":"https://uboat.net/allies/warships/ship/15004.html","quality_flags":null},"15005":{"built_by":"McLean (Renfrew, Scotland, U.K.)","ordered":"2 Sep 1940","laid_down":"","launched":"","commissioned":"12 Aug 1941","end_service":"","ordered_iso":"1940-09-02","laid_down_iso":null,"launched_iso":null,"commissioned_iso":"1941-08-12","end_service_iso":null,"history":"For disposal in December 1945","commanders":[],"url":"https://uboat.net/allies/warships/ship/15005.html","quality_flags":null},"15006":{"built_by":"McLean (Renfrew, Scotland, U.K.)","ordered":"2 Sep 1940","laid_down":"","launched":"","commissioned":"17 Nov 1941","end_service":"","ordered_iso":"1940-09-02","laid_down_iso":null,"launched_iso":null,"commissioned_iso":"1941-11-17","end_service_iso":null,"history":"For disposal in December 1945","commanders":[],"url":"https://uboat.net/allies/warships/ship/15006.html","quality_flags":null},"15007":{"built_by":"McLean (Renfrew, Scotland, U.K.)","ordered":"2 Sep 1940","laid_down":"","launched":"","commissioned":"6 Apr 1942","end_service":"1943","ordered_iso":"1940-09-02","laid_down_iso":null,"launched_iso":null,"commissioned_iso":"1942-04-06","end_service_iso":"1943-01-01","history":"Transferred to the Royal Indian Navy in 1943","commanders":[],"url":"https://uboat.net/allies/warships/ship/15007.html","quality_flags":null},"15008":{"built_by":"McLean (Renfrew, Scotland, U.K.)","ordered":"2 Sep 1940","laid_down":"","launched":"","commissioned":"1943","end_service":"","ordered_iso":"1940-09-02","laid_down_iso":null,"launched_iso":null,"commissioned_iso":"1943-01-01","end_service_iso":null,"history":"","commanders":[],"url":"https://uboat.net/allies/warships/ship/15008.html","quality_flags":null},"15009":{"built_by":"Elkins (Christchurch, England, U.K.)","ordered":"2 Sep 1940","laid_down":"","launched":"","commissioned":"8 Oct 1941","end_service":"","ordered_iso":"1940-09-02","laid_down_iso":null,"launched_iso":null,"commissioned_iso":"1941-10-08","end_service_iso":null,"history":"Transferred to Malaya on 22 June 1951","commanders":[],"url":"https://uboat.net/allies/warships/ship/15009.html","quality_flags":null},"15010":{"built_by":"Bolson (Poole, England, U.K.)","ordered":"2 Sep 1940","laid_down":"","launched":"","commissioned":"19 Sep 1941","end_service":"","ordered_iso":"1940-09-02","laid_down_iso":null,"launched_iso":null,"commissioned_iso":"1941-09-19","end_service_iso":null,"history":"","commanders":[],"url":"https://uboat.net/allies/warships/ship/15010.html","quality_flags":null},"15011":{"built_by":"Bolson (Poole, England, U.K.)","ordered":"2 Sep 1940","laid_down":"","launched":"","commissioned":"1 Dec 1941","end_service":"","ordered_iso":"1940-09-02","laid_down_iso":null,"launched_iso":null,"commissioned_iso":"1941-12-01","end_service_iso":null,"history":"Sold on 22 July 1947","commanders":[],"url":"https://uboat.net/allies/warships/ship/15011.html","quality_flags":null},"15012":{"built_by":"Blackmore (Bideford, U.K.)","ordered":"2 Sep 1940","laid_down":"","launched":"","commissioned":"23 Oct 1941","end_service":"","ordered_iso":"1940-09-02","laid_down_iso":null,"launched_iso":null,"commissioned_iso":"1941-10-23","end_service_iso":null,"history":"Grounded and lost in Aegean on 20 February 1944","commanders":[],"url":"https://uboat.net/allies/warships/ship/15012.html","quality_flags":null},"15013":{"built_by":"Blackmore (Bideford, U.K.)","ordered":"2 Sep 1940","laid_down":"","launched":"","commissioned":"19 Jan 1942","end_service":"2 Apr 1942","ordered_iso":"1940-09-02","laid_down_iso":null,"launched_iso":null,"commissioned_iso":"1942-01-19","end_service_iso":"1942-04-02","history":"Transferred to the Royal Indian Navy on 2 April 1942","commanders":[],"url":"https://uboat.net/allies/warships/ship/15013.html","quality_flags":null},"15014":{"built_by":"Blackmore (Bideford, U.K.)","ordered":"2 Sep 1940","laid_down":"","launched":"","commissioned":"2 Apr 1942","end_service":"1946","ordered_iso":"1940-09-02","laid_down_iso":null,"launched_iso":null,"commissioned_iso":"1942-04-02","end_service_iso":"1946-01-01","history":"Returned to the Royal Navy in 1946","commanders":[],"url":"https://uboat.net/allies/warships/ship/15014.html","quality_flags":null},"15015":{"built_by":"Sussex Ship Building Co. (Shoreham, England, U.K.)","ordered":"14 Oct 1940","laid_down":"","launched":"","commissioned":"16 Sep 1941","end_service":"","ordered_iso":"1940-10-14","laid_down_iso":null,"launched_iso":null,"commissioned_iso":"1941-09-16","end_service_iso":null,"history":"Sold on 9 June 1959","commanders":[],"url":"https://uboat.net/allies/warships/ship/15015.html","quality_flags":null},"15016":{"built_by":"Sussex Ship Building Co. (Shoreham, England, U.K.)","ordered":"14 Oct 1940","laid_down":"","launched":"","commissioned":"4 Nov 1941","end_service":"","ordered_iso":"1940-10-14","laid_down_iso":null,"launched_iso":null,"commissioned_iso":"1941-11-04","end_service_iso":null,"history":"For disposal in October 1946","commanders":[],"url":"https://uboat.net/allies/warships/ship/15016.html","quality_flags":null},"15017":{"built_by":"Sussex Ship Building Co. (Shoreham, England, U.K.)","ordered":"14 Oct 1940","laid_down":"","launched":"","commissioned":"3 Jan 1942","end_service":"","ordered_iso":"1940-10-14","laid_down_iso":null,"launched_iso":null,"commissioned_iso":"1942-01-03","end_service_iso":null,"history":"Transferred to the Royal Indian Navy on 2 April 1942Returned to the Royal Navy in 1944","commanders":[],"url":"https://uboat.net/allies/warships/ship/15017.html","quality_flags":null},"15018":{"built_by":"Sussex Ship Building Co. (Shoreham, England, U.K.)","ordered":"14 Oct 1940","laid_down":"","launched":"","commissioned":"2 Apr 1942","end_service":"1944","ordered_iso":"1940-10-14","laid_down_iso":null,"launched_iso":null,"commissioned_iso":"1942-04-02","end_service_iso":"1944-01-01","history":"Returned to the Royal Navy in 1944","commanders":[],"url":"https://uboat.net/allies/warships/ship/15018.html","quality_flags":null},"15019":{"built_by":"McGruer (Clynder, Scotland, U.K.)","ordered":"18 Oct 1940","laid_down":"","launched":"","commissioned":"24 Nov 1941","end_service":"","ordered_iso":"1940-10-18","laid_down_iso":null,"launched_iso":null,"commissioned_iso":"1941-11-24","end_service_iso":null,"history":"Sold in 1946","commanders":[],"url":"https://uboat.net/allies/warships/ship/15019.html","quality_flags":null},"15020":{"built_by":"McGruer (Clynder, Scotland, U.K.)","ordered":"18 Oct 1940","laid_down":"","launched":"","commissioned":"29 May 1942","end_service":"","ordered_iso":"1940-10-18","laid_down_iso":null,"launched_iso":null,"commissioned_iso":"1942-05-29","end_service_iso":null,"history":"For disposal in January 1946","commanders":[],"url":"https://uboat.net/allies/warships/ship/15020.html","quality_flags":null},"15021":{"built_by":"Ranalah Yacht Yard (Wooton, England, U.K.)","ordered":"14 Oct 1940","laid_down":"","launched":"","commissioned":"22 Jan 1942","end_service":"","ordered_iso":"1940-10-14","laid_down_iso":null,"launched_iso":null,"commissioned_iso":"1942-01-22","end_service_iso":null,"history":"Transferred to the Royal New Zealand Navy in June 1942","commanders":[],"url":"https://uboat.net/allies/warships/ship/15021.html","quality_flags":null},"15022":{"built_by":"Ranalah Yacht Yard (Wooton, England, U.K.)","ordered":"14 Oct 1940","laid_down":"","launched":"","commissioned":"Jun 1942","end_service":"11 Jul 1942","ordered_iso":"1940-10-14","laid_down_iso":null,"launched_iso":null,"commissioned_iso":"1942-06-01","end_service_iso":"1942-07-11","history":"Lost on 11 July 1942, during transport towards New Zealand","commanders":[],"url":"https://uboat.net/allies/warships/ship/15022.html","quality_flags":null},"15023":{"built_by":"Ranalah Yacht Yard (Wooton, England, U.K.)","ordered":"14 Oct 1940","laid_down":"","launched":"","commissioned":"16 Jul 1942","end_service":"","ordered_iso":"1940-10-14","laid_down_iso":null,"launched_iso":null,"commissioned_iso":"1942-07-16","end_service_iso":null,"history":"Sold on 22 July 1958","commanders":[],"url":"https://uboat.net/allies/warships/ship/15023.html","quality_flags":null},"15024":{"built_by":"Harland & Wolff (Belfast, Northern Ireland)","ordered":"14 Oct 1940","laid_down":"","launched":"","commissioned":"","end_service":"","ordered_iso":"1940-10-14","laid_down_iso":null,"launched_iso":null,"commissioned_iso":null,"end_service_iso":null,"history":"Destroyed on the stocks by German bombing in April / May 1941","commanders":[],"url":"https://uboat.net/allies/warships/ship/15024.html","quality_flags":null},"15025":{"built_by":"Harland & Wolff (Belfast, Northern Ireland)","ordered":"23 Oct 1940","laid_down":"","launched":"","commissioned":"","end_service":"","ordered_iso":"1940-10-23","laid_down_iso":null,"launched_iso":null,"commissioned_iso":null,"end_service_iso":null,"history":"Destroyed on the stocks by German bombing in April / May 1941","commanders":[],"url":"https://uboat.net/allies/warships/ship/15025.html","quality_flags":null},"15026":{"built_by":"Harland & Wolff (Belfast, Northern Ireland)","ordered":"23 Oct 1940","laid_down":"","launched":"","commissioned":"","end_service":"","ordered_iso":"1940-10-23","laid_down_iso":null,"launched_iso":null,"commissioned_iso":null,"end_service_iso":null,"history":"Destroyed on the stocks by German bombing in April / May 1941","commanders":[],"url":"https://uboat.net/allies/warships/ship/15026.html","quality_flags":null},"15027":{"built_by":"Harland & Wolff (Belfast, Northern Ireland)","ordered":"23 Oct 1940","laid_down":"","launched":"","commissioned":"","end_service":"","ordered_iso":"1940-10-23","laid_down_iso":null,"launched_iso":null,"commissioned_iso":null,"end_service_iso":null,"history":"Destroyed on the stocks by German bombing in April / May 1941","commanders":[],"url":"https://uboat.net/allies/warships/ship/15027.html","quality_flags":null},"15028":{"built_by":"Thornycroft (Singapore)","ordered":"27 Dec 1940","laid_down":"","launched":"1 Jun 1941","commissioned":"","end_service":"","ordered_iso":"1940-12-27","laid_down_iso":null,"launched_iso":"1941-06-01","commissioned_iso":null,"end_service_iso":null,"history":"Lost incomplete in February 1942 at Singapore","commanders":[],"url":"https://uboat.net/allies/warships/ship/15028.html","quality_flags":null},"15029":{"built_by":"Thornycroft (Singapore)","ordered":"27 Dec 1940","laid_down":"","launched":"10 Jun 1941","commissioned":"","end_service":"","ordered_iso":"1940-12-27","laid_down_iso":null,"launched_iso":"1941-06-10","commissioned_iso":null,"end_service_iso":null,"history":"Lost incomplete in February 1942 at Singapore","commanders":[],"url":"https://uboat.net/allies/warships/ship/15029.html","quality_flags":null},"15030":{"built_by":"Nichol (Durban, South Africa)","ordered":"27 Dec 1940","laid_down":"","launched":"","commissioned":"Feb 1942","end_service":"","ordered_iso":"1940-12-27","laid_down_iso":null,"launched_iso":null,"commissioned_iso":"1942-02-01","end_service_iso":null,"history":"For disposal in January 1947","commanders":[],"url":"https://uboat.net/allies/warships/ship/15030.html","quality_flags":null},"15031":{"built_by":"Nichol (Durban, South Africa)","ordered":"27 Dec 1940","laid_down":"","launched":"","commissioned":"1942","end_service":"","ordered_iso":"1940-12-27","laid_down_iso":null,"launched_iso":null,"commissioned_iso":"1942-01-01","end_service_iso":null,"history":"For disposal in January 1946","commanders":[],"url":"https://uboat.net/allies/warships/ship/15031.html","quality_flags":null},"15032":{"built_by":"Irrawadi Flottilla Co. (Rangoon, Burma)","ordered":"15 May 1940","laid_down":"","launched":"","commissioned":"Jul 1941","end_service":"","ordered_iso":"1940-05-15","laid_down_iso":null,"launched_iso":null,"commissioned_iso":"1941-07-01","end_service_iso":null,"history":"Transferred to the Royal Indian Navy in 1944","commanders":[],"url":"https://uboat.net/allies/warships/ship/15032.html","quality_flags":null},"15033":{"built_by":"Irrawadi Flottilla Co. (Rangoon, Burma)","ordered":"15 May 1940","laid_down":"","launched":"","commissioned":"1944","end_service":"","ordered_iso":"1940-05-15","laid_down_iso":null,"launched_iso":null,"commissioned_iso":"1944-01-01","end_service_iso":null,"history":"Sold in 1947","commanders":[],"url":"https://uboat.net/allies/warships/ship/15033.html","quality_flags":null},"15034":{"built_by":"Irrawadi Flottilla Co. (Rangoon, Burma)","ordered":"15 May 1940","laid_down":"","launched":"","commissioned":"Jul 1941","end_service":"","ordered_iso":"1940-05-15","laid_down_iso":null,"launched_iso":null,"commissioned_iso":"1941-07-01","end_service_iso":null,"history":"Transferred to the Royal Indian Navy in 1944","commanders":[],"url":"https://uboat.net/allies/warships/ship/15034.html","quality_flags":null},"15035":{"built_by":"Irrawadi Flottilla Co. (Rangoon, Burma)","ordered":"15 May 1940","laid_down":"","launched":"","commissioned":"1944","end_service":"","ordered_iso":"1940-05-15","laid_down_iso":null,"launched_iso":null,"commissioned_iso":"1944-01-01","end_service_iso":null,"history":"Sold in 1947","commanders":[],"url":"https://uboat.net/allies/warships/ship/15035.html","quality_flags":null},"15036":{"built_by":"Irrawadi Flottilla Co. (Rangoon, Burma)","ordered":"15 May 1940","laid_down":"","launched":"","commissioned":"Oct 1941","end_service":"","ordered_iso":"1940-05-15","laid_down_iso":null,"launched_iso":null,"commissioned_iso":"1941-10-01","end_service_iso":null,"history":"Transferred to the Royal Indian Navy in 1944","commanders":[],"url":"https://uboat.net/allies/warships/ship/15036.html","quality_flags":null},"15037":{"built_by":"Irrawadi Flottilla Co. (Rangoon, Burma)","ordered":"15 May 1940","laid_down":"","launched":"","commissioned":"1944","end_service":"","ordered_iso":"1940-05-15","laid_down_iso":null,"launched_iso":null,"commissioned_iso":"1944-01-01","end_service_iso":null,"history":"For disposal in March 1947","commanders":[],"url":"https://uboat.net/allies/warships/ship/15037.html","quality_flags":null},"15038":{"built_by":"Irrawadi Flottilla Co. (Rangoon, Burma)","ordered":"15 May 1940","laid_down":"","launched":"","commissioned":"Oct 1941","end_service":"","ordered_iso":"1940-05-15","laid_down_iso":null,"launched_iso":null,"commissioned_iso":"1941-10-01","end_service_iso":null,"history":"Transferred to the Royal Indian Navy in 1944","commanders":[],"url":"https://uboat.net/allies/warships/ship/15038.html","quality_flags":null},"15039":{"built_by":"Irrawadi Flottilla Co. (Rangoon, Burma)","ordered":"15 May 1940","laid_down":"","launched":"","commissioned":"1944","end_service":"","ordered_iso":"1940-05-15","laid_down_iso":null,"launched_iso":null,"commissioned_iso":"1944-01-01","end_service_iso":null,"history":"Sold in 1947","commanders":[],"url":"https://uboat.net/allies/warships/ship/15039.html","quality_flags":null},"15040":{"built_by":"Rangoon Govt. Dockyard (Rangoon, Burma)","ordered":"15 May 1940","laid_down":"","launched":"","commissioned":"30 Jun 1941","end_service":"","ordered_iso":"1940-05-15","laid_down_iso":null,"launched_iso":null,"commissioned_iso":"1941-06-30","end_service_iso":null,"history":"Transferred to the Royal Indian Navy in 1944","commanders":[],"url":"https://uboat.net/allies/warships/ship/15040.html","quality_flags":null},"15041":{"built_by":"Rangoon Govt. Dockyard (Rangoon, Burma)","ordered":"15 May 1940","laid_down":"","launched":"","commissioned":"1944","end_service":"","ordered_iso":"1940-05-15","laid_down_iso":null,"launched_iso":null,"commissioned_iso":"1944-01-01","end_service_iso":null,"history":"Sold in 1947","commanders":[],"url":"https://uboat.net/allies/warships/ship/15041.html","quality_flags":null},"15042":{"built_by":"Africa Marine (Mombasa, Kenya)","ordered":"27 Nov 1940","laid_down":"","launched":"","commissioned":"3 Mar 1943","end_service":"","ordered_iso":"1940-11-27","laid_down_iso":null,"launched_iso":null,"commissioned_iso":"1943-03-03","end_service_iso":null,"history":"Transferred to Malaya in 1949","commanders":[],"url":"https://uboat.net/allies/warships/ship/15042.html","quality_flags":null},"15043":{"built_by":"Africa Marine (Mombasa, Kenya)","ordered":"27 Nov 1940","laid_down":"","launched":"","commissioned":"3 Aug 1943","end_service":"","ordered_iso":"1940-11-27","laid_down_iso":null,"launched_iso":null,"commissioned_iso":"1943-08-03","end_service_iso":null,"history":"Sold to Portugal on 20 April 1947","commanders":[],"url":"https://uboat.net/allies/warships/ship/15043.html","quality_flags":null},"15044":{"built_by":"Africa Marine (Mombasa, Kenya)","ordered":"27 Nov 1940","laid_down":"","launched":"","commissioned":"30 Nov 1943","end_service":"","ordered_iso":"1940-11-27","laid_down_iso":null,"launched_iso":null,"commissioned_iso":"1943-11-30","end_service_iso":null,"history":"Sold in April 1948","commanders":[],"url":"https://uboat.net/allies/warships/ship/15044.html","quality_flags":null},"15045":{"built_by":"Africa Marine (Mombasa, Kenya)","ordered":"27 Nov 1940","laid_down":"","launched":"","commissioned":"6 Jun 1944","end_service":"","ordered_iso":"1940-11-27","laid_down_iso":null,"launched_iso":null,"commissioned_iso":"1944-06-06","end_service_iso":null,"history":"Sold to Portugal on 20 April 1947","commanders":[],"url":"https://uboat.net/allies/warships/ship/15045.html","quality_flags":null},"15046":{"built_by":"Mohatta (Karachi, British India)","ordered":"8 Jan 1942","laid_down":"","launched":"","commissioned":"15 May 1944","end_service":"","ordered_iso":"1942-01-08","laid_down_iso":null,"launched_iso":null,"commissioned_iso":"1944-05-15","end_service_iso":null,"history":"Sold in 1947","commanders":[],"url":"https://uboat.net/allies/warships/ship/15046.html","quality_flags":null},"15047":{"built_by":"Mohatta (Karachi, British India)","ordered":"8 Jan 1942","laid_down":"","launched":"","commissioned":"1 May 1944","end_service":"","ordered_iso":"1942-01-08","laid_down_iso":null,"launched_iso":null,"commissioned_iso":"1944-05-01","end_service_iso":null,"history":"","commanders":[],"url":"https://uboat.net/allies/warships/ship/15047.html","quality_flags":null},"15048":{"built_by":"Mohatta (Karachi, British India)","ordered":"8 Jan 1942","laid_down":"","launched":"","commissioned":"Jun 1944","end_service":"","ordered_iso":"1942-01-08","laid_down_iso":null,"launched_iso":null,"commissioned_iso":"1944-06-01","end_service_iso":null,"history":"Sold in 1947","commanders":[],"url":"https://uboat.net/allies/warships/ship/15048.html","quality_flags":null},"15049":{"built_by":"Hooghly Docking & Engineering Company, Ltd. (Calcutta, India)","ordered":"8 Jan 1942","laid_down":"","launched":"","commissioned":"6 Dec 1944","end_service":"","ordered_iso":"1942-01-08","laid_down_iso":null,"launched_iso":null,"commissioned_iso":"1944-12-06","end_service_iso":null,"history":"","commanders":[],"url":"https://uboat.net/allies/warships/ship/15049.html","quality_flags":null},"15050":{"built_by":"Hooghly Docking & Engineering Company, Ltd. (Calcutta, India)","ordered":"8 Jan 1942","laid_down":"","launched":"","commissioned":"24 Dec 1944","end_service":"","ordered_iso":"1942-01-08","laid_down_iso":null,"launched_iso":null,"commissioned_iso":"1944-12-24","end_service_iso":null,"history":"Sold in 1947","commanders":[],"url":"https://uboat.net/allies/warships/ship/15050.html","quality_flags":null},"15051":{"built_by":"Bombay Steam Navigation (Bombay, India)","ordered":"8 Jan 1942","laid_down":"","launched":"","commissioned":"21 Jan 1944","end_service":"","ordered_iso":"1942-01-08","laid_down_iso":null,"launched_iso":null,"commissioned_iso":"1944-01-21","end_service_iso":null,"history":"For disposal in November 1946","commanders":[],"url":"https://uboat.net/allies/warships/ship/15051.html","quality_flags":null},"15052":{"built_by":"Garden Reach Shipbuilders & Engineers Ltd. (Calcutta, India)","ordered":"8 Jan 1942","laid_down":"","launched":"","commissioned":"10 Jun 1943","end_service":"","ordered_iso":"1942-01-08","laid_down_iso":null,"launched_iso":null,"commissioned_iso":"1943-06-10","end_service_iso":null,"history":"For disposal in November 1946","commanders":[],"url":"https://uboat.net/allies/warships/ship/15052.html","quality_flags":null},"15053":{"built_by":"Bombay Naval Dockyard (Bombay, India)","ordered":"8 Jan 1942","laid_down":"","launched":"","commissioned":"Apr 1944","end_service":"","ordered_iso":"1942-01-08","laid_down_iso":null,"launched_iso":null,"commissioned_iso":"1944-04-01","end_service_iso":null,"history":"For disposal in November 1946","commanders":[],"url":"https://uboat.net/allies/warships/ship/15053.html","quality_flags":null},"15054":{"built_by":"Bombay Naval Dockyard (Bombay, India)","ordered":"8 Jan 1942","laid_down":"","launched":"","commissioned":"23 Mar 1944","end_service":"","ordered_iso":"1942-01-08","laid_down_iso":null,"launched_iso":null,"commissioned_iso":"1944-03-23","end_service_iso":null,"history":"","commanders":[],"url":"https://uboat.net/allies/warships/ship/15054.html","quality_flags":null},"15055":{"built_by":"India General Navigation (Calcutta, India)","ordered":"8 Jan 1942","laid_down":"","launched":"","commissioned":"11 Nov 1944","end_service":"","ordered_iso":"1942-01-08","laid_down_iso":null,"launched_iso":null,"commissioned_iso":"1944-11-11","end_service_iso":null,"history":"","commanders":[],"url":"https://uboat.net/allies/warships/ship/15055.html","quality_flags":null},"15056":{"built_by":"India General Navigation (Calcutta, India)","ordered":"8 Jan 1942","laid_down":"","launched":"","commissioned":"27 Jul 1944","end_service":"","ordered_iso":"1942-01-08","laid_down_iso":null,"launched_iso":null,"commissioned_iso":"1944-07-27","end_service_iso":null,"history":"Sunk off Maungdaw, Burma on 7 October 1944 after an attack by friendly aircraft","commanders":[],"url":"https://uboat.net/allies/warships/ship/15056.html","quality_flags":null},"15057":{"built_by":"Garden Reach Shipbuilders & Engineers Ltd. (Calcutta, India)","ordered":"8 Jan 1942","laid_down":"","launched":"","commissioned":"22 Jul 1943","end_service":"","ordered_iso":"1942-01-08","laid_down_iso":null,"launched_iso":null,"commissioned_iso":"1943-07-22","end_service_iso":null,"history":"Sold in 1947","commanders":[],"url":"https://uboat.net/allies/warships/ship/15057.html","quality_flags":null},"15058":{"built_by":"Sussex Ship Building Co. (Shoreham, England, U.K.)","ordered":"30 May 1941","laid_down":"","launched":"","commissioned":"10 Jul 1942","end_service":"","ordered_iso":"1941-05-30","laid_down_iso":null,"launched_iso":null,"commissioned_iso":"1942-07-10","end_service_iso":null,"history":"Foundered off Pantelleria Island on 31 December 1943","commanders":[],"url":"https://uboat.net/allies/warships/ship/15058.html","quality_flags":null},"15059":{"built_by":"Sussex Ship Building Co. (Shoreham, England, U.K.)","ordered":"30 May 1941","laid_down":"","launched":"","commissioned":"29 May 1942","end_service":"","ordered_iso":"1941-05-30","laid_down_iso":null,"launched_iso":null,"commissioned_iso":"1942-05-29","end_service_iso":null,"history":"Sold in 1946","commanders":[],"url":"https://uboat.net/allies/warships/ship/15059.html","quality_flags":null},"15060":{"built_by":"Sussex Ship Building Co. (Shoreham, England, U.K.)","ordered":"30 May 1941","laid_down":"","launched":"","commissioned":"2 Aug 1942","end_service":"","ordered_iso":"1941-05-30","laid_down_iso":null,"launched_iso":null,"commissioned_iso":"1942-08-02","end_service_iso":null,"history":"Sold in October 1946","commanders":[],"url":"https://uboat.net/allies/warships/ship/15060.html","quality_flags":null},"15061":{"built_by":"Sussex Ship Building Co. (Shoreham, England, U.K.)","ordered":"30 May 1941","laid_down":"","launched":"","commissioned":"2 Oct 1942","end_service":"1943","ordered_iso":"1941-05-30","laid_down_iso":null,"launched_iso":null,"commissioned_iso":"1942-10-02","end_service_iso":"1943-01-01","history":"Transferred to Turkey in 1943","commanders":[],"url":"https://uboat.net/allies/warships/ship/15061.html","quality_flags":null},"15062":{"built_by":"Berthon Boat (Lymington, England, U.K.)","ordered":"30 May 1941","laid_down":"","launched":"","commissioned":"28 Apr 1942","end_service":"1943","ordered_iso":"1941-05-30","laid_down_iso":null,"launched_iso":null,"commissioned_iso":"1942-04-28","end_service_iso":"1943-01-01","history":"Transferred to the Royal Australian Navy in 1943","commanders":[],"url":"https://uboat.net/allies/warships/ship/15062.html","quality_flags":null},"15063":{"built_by":"Berthon Boat (Lymington, England, U.K.)","ordered":"30 May 1941","laid_down":"","launched":"","commissioned":"1943","end_service":"1944","ordered_iso":"1941-05-30","laid_down_iso":null,"launched_iso":null,"commissioned_iso":"1943-01-01","end_service_iso":"1944-01-01","history":"Transferred to the Royal Indian Navy in 1944","commanders":[],"url":"https://uboat.net/allies/warships/ship/15063.html","quality_flags":null},"15064":{"built_by":"Berthon Boat (Lymington, England, U.K.)","ordered":"30 May 1941","laid_down":"","launched":"","commissioned":"1944","end_service":"","ordered_iso":"1941-05-30","laid_down_iso":null,"launched_iso":null,"commissioned_iso":"1944-01-01","end_service_iso":null,"history":"Sold in 1947","commanders":[],"url":"https://uboat.net/allies/warships/ship/15064.html","quality_flags":null},"15065":{"built_by":"Berthon Boat (Lymington, England, U.K.)","ordered":"30 May 1941","laid_down":"","launched":"","commissioned":"21 May 1942","end_service":"","ordered_iso":"1941-05-30","laid_down_iso":null,"launched_iso":null,"commissioned_iso":"1942-05-21","end_service_iso":null,"history":"To Palestine on 27 June 1946","commanders":[],"url":"https://uboat.net/allies/warships/ship/15065.html","quality_flags":null},"15066":{"built_by":"Berthon Boat (Lymington, England, U.K.)","ordered":"30 May 1941","laid_down":"","launched":"","commissioned":"9 Jun 1942","end_service":"16 Nov 1943","ordered_iso":"1941-05-30","laid_down_iso":null,"launched_iso":null,"commissioned_iso":"1942-06-09","end_service_iso":"1943-11-16","history":"Transferred to the Free French Navy on 16 November 1943","commanders":[],"url":"https://uboat.net/allies/warships/ship/15066.html","quality_flags":null},"15067":{"built_by":"Berthon Boat (Lymington, England, U.K.)","ordered":"30 May 1941","laid_down":"","launched":"","commissioned":"16 Nov 1943","end_service":"","ordered_iso":"1941-05-30","laid_down_iso":null,"launched_iso":null,"commissioned_iso":"1943-11-16","end_service_iso":null,"history":"","commanders":[],"url":"https://uboat.net/allies/warships/ship/15067.html","quality_flags":null},"15068":{"built_by":"Berthon Boat (Lymington, England, U.K.)","ordered":"30 May 1941","laid_down":"","launched":"","commissioned":"30 Jun 1942","end_service":"1944","ordered_iso":"1941-05-30","laid_down_iso":null,"launched_iso":null,"commissioned_iso":"1942-06-30","end_service_iso":"1944-01-01","history":"Transferred to the Free French Navy in 1944","commanders":[],"url":"https://uboat.net/allies/warships/ship/15068.html","quality_flags":null},"15069":{"built_by":"Berthon Boat (Lymington, England, U.K.)","ordered":"30 May 1941","laid_down":"","launched":"","commissioned":"1944","end_service":"","ordered_iso":"1941-05-30","laid_down_iso":null,"launched_iso":null,"commissioned_iso":"1944-01-01","end_service_iso":null,"history":"","commanders":[],"url":"https://uboat.net/allies/warships/ship/15069.html","quality_flags":null},"15070":{"built_by":"Thornycroft (Hampton-on-Thames, England, U.K.)","ordered":"30 May 1941","laid_down":"","launched":"","commissioned":"23 Apr 1942","end_service":"7 Nov 1942","ordered_iso":"1941-05-30","laid_down_iso":null,"launched_iso":null,"commissioned_iso":"1942-04-23","end_service_iso":"1942-11-07","history":"Transferred to the Royal Australian Navy on 7 November 1942","commanders":[],"url":"https://uboat.net/allies/warships/ship/15070.html","quality_flags":null},"15071":{"built_by":"Thornycroft (Hampton-on-Thames, England, U.K.)","ordered":"30 May 1941","laid_down":"","launched":"","commissioned":"7 Nov 1942","end_service":"","ordered_iso":"1941-05-30","laid_down_iso":null,"launched_iso":null,"commissioned_iso":"1942-11-07","end_service_iso":null,"history":"","commanders":[],"url":"https://uboat.net/allies/warships/ship/15071.html","quality_flags":null},"15072":{"built_by":"Thornycroft (Hampton-on-Thames, England, U.K.)","ordered":"30 May 1941","laid_down":"","launched":"","commissioned":"30 Apr 1942","end_service":"","ordered_iso":"1941-05-30","laid_down_iso":null,"launched_iso":null,"commissioned_iso":"1942-04-30","end_service_iso":null,"history":"Sold in 1946","commanders":["T/S.Lt. Clifford Sigmund Booth, RNVR (Apr 1942 - 15 Jan 1944)","T/Lt. Maurice Sydney Osmond, RANVR (15 Jan 1944 - early 1945)"],"url":"https://uboat.net/allies/warships/ship/15072.html","quality_flags":null},"15073":{"built_by":"Thornycroft (Hampton-on-Thames, England, U.K.)","ordered":"30 May 1941","laid_down":"","launched":"","commissioned":"12 May 1942","end_service":"","ordered_iso":"1941-05-30","laid_down_iso":null,"launched_iso":null,"commissioned_iso":"1942-05-12","end_service_iso":null,"history":"Sold in 1946","commanders":[],"url":"https://uboat.net/allies/warships/ship/15073.html","quality_flags":null},"15074":{"built_by":"Thornycroft (Hampton-on-Thames, England, U.K.)","ordered":"30 May 1941","laid_down":"","launched":"","commissioned":"13 Jun 1942","end_service":"20 Sep 1943","ordered_iso":"1941-05-30","laid_down_iso":null,"launched_iso":null,"commissioned_iso":"1942-06-13","end_service_iso":"1943-09-20","history":"Transferred to the Free French Navy on 20 September 1943","commanders":[],"url":"https://uboat.net/allies/warships/ship/15074.html","quality_flags":null},"15075":{"built_by":"Thornycroft (Hampton-on-Thames, England, U.K.)","ordered":"30 May 1941","laid_down":"","launched":"","commissioned":"20 Sep 1943","end_service":"","ordered_iso":"1941-05-30","laid_down_iso":null,"launched_iso":null,"commissioned_iso":"1943-09-20","end_service_iso":null,"history":"","commanders":[],"url":"https://uboat.net/allies/warships/ship/15075.html","quality_flags":null},"15076":{"built_by":"Thornycroft (Hampton-on-Thames, England, U.K.)","ordered":"30 May 1941","laid_down":"","launched":"","commissioned":"27 Jun 1942","end_service":"1 Sep 1943","ordered_iso":"1941-05-30","laid_down_iso":null,"launched_iso":null,"commissioned_iso":"1942-06-27","end_service_iso":"1943-09-01","history":"Transferred to the Free French Navy on 1 September 1943","commanders":[],"url":"https://uboat.net/allies/warships/ship/15076.html","quality_flags":null},"15077":{"built_by":"Thornycroft (Hampton-on-Thames, England, U.K.)","ordered":"30 May 1941","laid_down":"","launched":"","commissioned":"1 Sep 1943","end_service":"","ordered_iso":"1941-05-30","laid_down_iso":null,"launched_iso":null,"commissioned_iso":"1943-09-01","end_service_iso":null,"history":"","commanders":[],"url":"https://uboat.net/allies/warships/ship/15077.html","quality_flags":null},"15078":{"built_by":"Thornycroft (Hampton-on-Thames, England, U.K.)","ordered":"30 May 1941","laid_down":"","launched":"","commissioned":"13 Aug 1942","end_service":"","ordered_iso":"1941-05-30","laid_down_iso":null,"launched_iso":null,"commissioned_iso":"1942-08-13","end_service_iso":null,"history":"For disposal in July 1946","commanders":[],"url":"https://uboat.net/allies/warships/ship/15078.html","quality_flags":null},"15079":{"built_by":"Thornycroft (Hampton-on-Thames, England, U.K.)","ordered":"30 May 1941","laid_down":"","launched":"","commissioned":"18 Sep 1942","end_service":"May 1943","ordered_iso":"1941-05-30","laid_down_iso":null,"launched_iso":null,"commissioned_iso":"1942-09-18","end_service_iso":"1943-05-01","history":"Transferred to Turkey in May 1943","commanders":[],"url":"https://uboat.net/allies/warships/ship/15079.html","quality_flags":null},"15080":{"built_by":"Thornycroft (Hampton-on-Thames, England, U.K.)","ordered":"30 May 1941","laid_down":"","launched":"","commissioned":"22 Oct 1942","end_service":"1944","ordered_iso":"1941-05-30","laid_down_iso":null,"launched_iso":null,"commissioned_iso":"1942-10-22","end_service_iso":"1944-01-01","history":"Transferred to the Free French Navy in 1944 being renamed VP 14. Broken up at Saigon in the 50's.","commanders":["T/Lt. Leonard John Wayman, RNVR (21 Sep 1942 - )"],"url":"https://uboat.net/allies/warships/ship/15080.html","quality_flags":null},"15081":{"built_by":"Thornycroft (Hampton-on-Thames, England, U.K.)","ordered":"30 May 1941","laid_down":"","launched":"","commissioned":"1944","end_service":"","ordered_iso":"1941-05-30","laid_down_iso":null,"launched_iso":null,"commissioned_iso":"1944-01-01","end_service_iso":null,"history":"","commanders":[],"url":"https://uboat.net/allies/warships/ship/15081.html","quality_flags":null},"15082":{"built_by":"Robinson (Lowestoft, England, U.K.)","ordered":"30 May 1941","laid_down":"","launched":"","commissioned":"10 Sep 1942","end_service":"","ordered_iso":"1941-05-30","laid_down_iso":null,"launched_iso":null,"commissioned_iso":"1942-09-10","end_service_iso":null,"history":"Sold on 18 December 1945","commanders":[],"url":"https://uboat.net/allies/warships/ship/15082.html","quality_flags":null},"15083":{"built_by":"Robinson (Lowestoft, England, U.K.)","ordered":"30 May 1941","laid_down":"","launched":"","commissioned":"17 Nov 1942","end_service":"May 1943","ordered_iso":"1941-05-30","laid_down_iso":null,"launched_iso":null,"commissioned_iso":"1942-11-17","end_service_iso":"1943-05-01","history":"Transferred to the Free French Navy in May 1943","commanders":[],"url":"https://uboat.net/allies/warships/ship/15083.html","quality_flags":null},"15084":{"built_by":"Robinson (Lowestoft, England, U.K.)","ordered":"30 May 1941","laid_down":"","launched":"","commissioned":"May 1943","end_service":"","ordered_iso":"1941-05-30","laid_down_iso":null,"launched_iso":null,"commissioned_iso":"1943-05-01","end_service_iso":null,"history":"","commanders":[],"url":"https://uboat.net/allies/warships/ship/15084.html","quality_flags":null},"15085":{"built_by":"Robinson (Tewkesbury, England, U.K.)","ordered":"30 May 1941","laid_down":"","launched":"","commissioned":"3 Jul 1942","end_service":"1944","ordered_iso":"1941-05-30","laid_down_iso":null,"launched_iso":null,"commissioned_iso":"1942-07-03","end_service_iso":"1944-01-01","history":"Transferred to the Free French Navy in 1944","commanders":[],"url":"https://uboat.net/allies/warships/ship/15085.html","quality_flags":null},"15086":{"built_by":"Robinson (Tewkesbury, England, U.K.)","ordered":"30 May 1941","laid_down":"","launched":"","commissioned":"1944","end_service":"","ordered_iso":"1941-05-30","laid_down_iso":null,"launched_iso":null,"commissioned_iso":"1944-01-01","end_service_iso":null,"history":"","commanders":[],"url":"https://uboat.net/allies/warships/ship/15086.html","quality_flags":null},"15087":{"built_by":"Bolson (Poole, England, U.K.)","ordered":"30 May 1941","laid_down":"","launched":"","commissioned":"19 Jun 1942","end_service":"","ordered_iso":"1941-05-30","laid_down_iso":null,"launched_iso":null,"commissioned_iso":"1942-06-19","end_service_iso":null,"history":"Sold on 1 March 1957","commanders":[],"url":"https://uboat.net/allies/warships/ship/15087.html","quality_flags":null},"15088":{"built_by":"Bolson (Poole, England, U.K.)","ordered":"30 May 1941","laid_down":"","launched":"","commissioned":"12 Oct 1942","end_service":"30 Aug 1943","ordered_iso":"1941-05-30","laid_down_iso":null,"launched_iso":null,"commissioned_iso":"1942-10-12","end_service_iso":"1943-08-30","history":"Transferred to the Free French Navy on 30 August 1943","commanders":[],"url":"https://uboat.net/allies/warships/ship/15088.html","quality_flags":null},"15089":{"built_by":"Bolson (Poole, England, U.K.)","ordered":"30 May 1941","laid_down":"","launched":"","commissioned":"30 Aug 1943","end_service":"","ordered_iso":"1941-05-30","laid_down_iso":null,"launched_iso":null,"commissioned_iso":"1943-08-30","end_service_iso":null,"history":"","commanders":[],"url":"https://uboat.net/allies/warships/ship/15089.html","quality_flags":null},"15090":{"built_by":"Woods (Potter Heigham, England, U.K.)","ordered":"30 May 1941","laid_down":"","launched":"","commissioned":"4 Jul 1942","end_service":"14 Jan 1944","ordered_iso":"1941-05-30","laid_down_iso":null,"launched_iso":null,"commissioned_iso":"1942-07-04","end_service_iso":"1944-01-14","history":"Transferred to the Free French Navy on 14 January 1944","commanders":[],"url":"https://uboat.net/allies/warships/ship/15090.html","quality_flags":null},"15091":{"built_by":"Woods (Potter Heigham, England, U.K.)","ordered":"30 May 1941","laid_down":"","launched":"","commissioned":"14 Jan 1944","end_service":"","ordered_iso":"1941-05-30","laid_down_iso":null,"launched_iso":null,"commissioned_iso":"1944-01-14","end_service_iso":null,"history":"","commanders":[],"url":"https://uboat.net/allies/warships/ship/15091.html","quality_flags":null},"15092":{"built_by":"Woods (Potter Heigham, England, U.K.)","ordered":"30 May 1941","laid_down":"","launched":"","commissioned":"20 Aug 1942","end_service":"1944","ordered_iso":"1941-05-30","laid_down_iso":null,"launched_iso":null,"commissioned_iso":"1942-08-20","end_service_iso":"1944-01-01","history":"Transferred to the Free French Navy in 1944","commanders":[],"url":"https://uboat.net/allies/warships/ship/15092.html","quality_flags":null},"15093":{"built_by":"Woods (Potter Heigham, England, U.K.)","ordered":"30 May 1941","laid_down":"","launched":"","commissioned":"1944","end_service":"","ordered_iso":"1941-05-30","laid_down_iso":null,"launched_iso":null,"commissioned_iso":"1944-01-01","end_service_iso":null,"history":"","commanders":[],"url":"https://uboat.net/allies/warships/ship/15093.html","quality_flags":null},"15094":{"built_by":"Woods (Potter Heigham, England, U.K.)","ordered":"30 May 1941","laid_down":"","launched":"","commissioned":"10 Nov 1942","end_service":"26 Feb 1944","ordered_iso":"1941-05-30","laid_down_iso":null,"launched_iso":null,"commissioned_iso":"1942-11-10","end_service_iso":"1944-02-26","history":"Transferred to the Free French Navy on 26 February 1944","commanders":[],"url":"https://uboat.net/allies/warships/ship/15094.html","quality_flags":null},"15095":{"built_by":"Woods (Potter Heigham, England, U.K.)","ordered":"30 May 1941","laid_down":"","launched":"","commissioned":"26 Feb 1944","end_service":"","ordered_iso":"1941-05-30","laid_down_iso":null,"launched_iso":null,"commissioned_iso":"1944-02-26","end_service_iso":null,"history":"","commanders":[],"url":"https://uboat.net/allies/warships/ship/15095.html","quality_flags":null},"15096":{"built_by":"Woods (Potter Heigham, England, U.K.)","ordered":"30 May 1941","laid_down":"","launched":"","commissioned":"26 Nov 1942","end_service":"","ordered_iso":"1941-05-30","laid_down_iso":null,"launched_iso":null,"commissioned_iso":"1942-11-26","end_service_iso":null,"history":"To Palestine on 5 January 1946","commanders":[],"url":"https://uboat.net/allies/warships/ship/15096.html","quality_flags":null},"15097":{"built_by":"Anderson Rigden & Perkins (Whitstable, England, U.K.)","ordered":"30 May 1941","laid_down":"","launched":"","commissioned":"6 Jun 1942","end_service":"","ordered_iso":"1941-05-30","laid_down_iso":null,"launched_iso":null,"commissioned_iso":"1942-06-06","end_service_iso":null,"history":"Sold in 1946","commanders":[],"url":"https://uboat.net/allies/warships/ship/15097.html","quality_flags":null},"15098":{"built_by":"Anderson Rigden & Perkins (Whitstable, England, U.K.)","ordered":"30 May 1941","laid_down":"","launched":"","commissioned":"22 May 1942","end_service":"","ordered_iso":"1941-05-30","laid_down_iso":null,"launched_iso":null,"commissioned_iso":"1942-05-22","end_service_iso":null,"history":"For disposal in June 1945","commanders":[],"url":"https://uboat.net/allies/warships/ship/15098.html","quality_flags":null},"15099":{"built_by":"Moody (Southampton, England, U.K.)","ordered":"30 May 1941","laid_down":"","launched":"","commissioned":"23 Apr 1942","end_service":"1943","ordered_iso":"1941-05-30","laid_down_iso":null,"launched_iso":null,"commissioned_iso":"1942-04-23","end_service_iso":"1943-01-01","history":"Transferred to the Royal Indian Navy in 1943","commanders":[],"url":"https://uboat.net/allies/warships/ship/15099.html","quality_flags":null},"15100":{"built_by":"Moody (Southampton, England, U.K.)","ordered":"30 May 1941","laid_down":"","launched":"","commissioned":"1943","end_service":"","ordered_iso":"1941-05-30","laid_down_iso":null,"launched_iso":null,"commissioned_iso":"1943-01-01","end_service_iso":null,"history":"Sold in 1947","commanders":[],"url":"https://uboat.net/allies/warships/ship/15100.html","quality_flags":null},"15101":{"built_by":"Moody (Southampton, England, U.K.)","ordered":"30 May 1941","laid_down":"","launched":"","commissioned":"29 May 1942","end_service":"4 Sep 1945","ordered_iso":"1941-05-30","laid_down_iso":null,"launched_iso":null,"commissioned_iso":"1942-05-29","end_service_iso":"1945-09-04","history":"Transferred to Greece on 4 September 1945","commanders":[],"url":"https://uboat.net/allies/warships/ship/15101.html","quality_flags":null},"15102":{"built_by":"Moody (Southampton, England, U.K.)","ordered":"30 May 1941","laid_down":"","launched":"","commissioned":"4 Sep 1945","end_service":"","ordered_iso":"1941-05-30","laid_down_iso":null,"launched_iso":null,"commissioned_iso":"1945-09-04","end_service_iso":null,"history":"","commanders":[],"url":"https://uboat.net/allies/warships/ship/15102.html","quality_flags":null},"15103":{"built_by":"Blackmore (Bideford, U.K.)","ordered":"30 May 1941","laid_down":"","launched":"","commissioned":"10 May 1942","end_service":"","ordered_iso":"1941-05-30","laid_down_iso":null,"launched_iso":null,"commissioned_iso":"1942-05-10","end_service_iso":null,"history":"Sold on 22 July 1947","commanders":[],"url":"https://uboat.net/allies/warships/ship/15103.html","quality_flags":null}}